mmpose/__init__.py
mmpose/registry.py
mmpose/version.py
mmpose/.mim/dataset-index.yml
mmpose/.mim/model-index.yml
mmpose/.mim/configs/_base_/default_runtime.py
mmpose/.mim/configs/_base_/datasets/300w.py
mmpose/.mim/configs/_base_/datasets/300wlp.py
mmpose/.mim/configs/_base_/datasets/aflw.py
mmpose/.mim/configs/_base_/datasets/aic.py
mmpose/.mim/configs/_base_/datasets/ak.py
mmpose/.mim/configs/_base_/datasets/animalpose.py
mmpose/.mim/configs/_base_/datasets/ap10k.py
mmpose/.mim/configs/_base_/datasets/atrw.py
mmpose/.mim/configs/_base_/datasets/campus.py
mmpose/.mim/configs/_base_/datasets/coco.py
mmpose/.mim/configs/_base_/datasets/coco_aic.py
mmpose/.mim/configs/_base_/datasets/coco_openpose.py
mmpose/.mim/configs/_base_/datasets/coco_wholebody.py
mmpose/.mim/configs/_base_/datasets/coco_wholebody_face.py
mmpose/.mim/configs/_base_/datasets/coco_wholebody_hand.py
mmpose/.mim/configs/_base_/datasets/coco_wholebody_openpose.py
mmpose/.mim/configs/_base_/datasets/cofw.py
mmpose/.mim/configs/_base_/datasets/crowdpose.py
mmpose/.mim/configs/_base_/datasets/deepfashion2.py
mmpose/.mim/configs/_base_/datasets/deepfashion_full.py
mmpose/.mim/configs/_base_/datasets/deepfashion_lower.py
mmpose/.mim/configs/_base_/datasets/deepfashion_upper.py
mmpose/.mim/configs/_base_/datasets/exlpose.py
mmpose/.mim/configs/_base_/datasets/fly.py
mmpose/.mim/configs/_base_/datasets/freihand2d.py
mmpose/.mim/configs/_base_/datasets/h36m.py
mmpose/.mim/configs/_base_/datasets/h3wb.py
mmpose/.mim/configs/_base_/datasets/halpe.py
mmpose/.mim/configs/_base_/datasets/halpe26.py
mmpose/.mim/configs/_base_/datasets/horse10.py
mmpose/.mim/configs/_base_/datasets/humanart.py
mmpose/.mim/configs/_base_/datasets/humanart21.py
mmpose/.mim/configs/_base_/datasets/humanart_aic.py
mmpose/.mim/configs/_base_/datasets/interhand2d.py
mmpose/.mim/configs/_base_/datasets/interhand3d.py
mmpose/.mim/configs/_base_/datasets/jhmdb.py
mmpose/.mim/configs/_base_/datasets/lapa.py
mmpose-1.3.1.dist-info/LICENSE
mmpose-1.3.1.dist-info/LICENSES.md
mmpose-1.3.1.dist-info/METADATA
mmpose-1.3.1.dist-info/WHEEL
mmpose-1.3.1.dist-info/top_level.txt
mmpose-1.3.1.dist-info/RECORD
