Metadata-Version: 2.1
Name: mmpose
Version: 1.3.1
Summary: OpenMMLab Pose Estimation Toolbox and Benchmark.
Home-page: https://github.com/open-mmlab/mmpose
Author: MMPose Contributors
Author-email: openmmlab@gmail.com
License: Apache License 2.0
Keywords: computer vision,pose estimation
Platform: UNKNOWN
Classifier: Development Status :: 4 - Beta
Classifier: License :: OSI Approved :: Apache Software License
Classifier: Operating System :: OS Independent
Classifier: Programming Language :: Python :: 3
Classifier: Programming Language :: Python :: 3.7
Classifier: Programming Language :: Python :: 3.8
Classifier: Programming Language :: Python :: 3.9
Requires-Python: >=3.7
Requires-Dist: chumpy
Requires-Dist: json-tricks
Requires-Dist: matplotlib
Requires-Dist: munkres
Requires-Dist: numpy
Requires-Dist: opencv-python
Requires-Dist: pillow
Requires-Dist: scipy
Requires-Dist: torchvision
Requires-Dist: xtcocotools >=1.12
Provides-Extra: all
Requires-Dist: numpy ; extra == 'all'
Requires-Dist: torch >=1.8 ; extra == 'all'
Requires-Dist: chumpy ; extra == 'all'
Requires-Dist: json-tricks ; extra == 'all'
Requires-Dist: matplotlib ; extra == 'all'
Requires-Dist: munkres ; extra == 'all'
Requires-Dist: opencv-python ; extra == 'all'
Requires-Dist: pillow ; extra == 'all'
Requires-Dist: scipy ; extra == 'all'
Requires-Dist: torchvision ; extra == 'all'
Requires-Dist: xtcocotools >=1.12 ; extra == 'all'
Requires-Dist: coverage ; extra == 'all'
Requires-Dist: flake8 ; extra == 'all'
Requires-Dist: interrogate ; extra == 'all'
Requires-Dist: isort ==4.3.21 ; extra == 'all'
Requires-Dist: parameterized ; extra == 'all'
Requires-Dist: pytest ; extra == 'all'
Requires-Dist: pytest-runner ; extra == 'all'
Requires-Dist: xdoctest >=0.10.0 ; extra == 'all'
Requires-Dist: yapf ; extra == 'all'
Requires-Dist: requests ; extra == 'all'
Provides-Extra: mim
Requires-Dist: mmcv <2.2.0,>=2.0.0 ; extra == 'mim'
Requires-Dist: mmdet <3.3.0,>=3.0.0 ; extra == 'mim'
Requires-Dist: mmengine <1.0.0,>=0.4.0 ; extra == 'mim'
Provides-Extra: optional
Requires-Dist: requests ; extra == 'optional'
Provides-Extra: tests
Requires-Dist: coverage ; extra == 'tests'
Requires-Dist: flake8 ; extra == 'tests'
Requires-Dist: interrogate ; extra == 'tests'
Requires-Dist: isort ==4.3.21 ; extra == 'tests'
Requires-Dist: parameterized ; extra == 'tests'
Requires-Dist: pytest ; extra == 'tests'
Requires-Dist: pytest-runner ; extra == 'tests'
Requires-Dist: xdoctest >=0.10.0 ; extra == 'tests'
Requires-Dist: yapf ; extra == 'tests'
